mir/winenv/__init__.py
mir/winenv/__main__.py
mir/winenv/configlib.py
mir/winenv/shells.py
mir.winenv-0.4.0.dist-info/DESCRIPTION.rst
mir.winenv-0.4.0.dist-info/METADATA
mir.winenv-0.4.0.dist-info/RECORD
mir.winenv-0.4.0.dist-info/WHEEL
mir.winenv-0.4.0.dist-info/metadata.json
mir.winenv-0.4.0.dist-info/top_level.txt
