Metadata-Version: 2.0
Name: mir.winenv
Version: 0.4.0
Summary: Manage Wine environments
Home-page: https://github.com/darkfeline/mir.winenv
Author: Allen Li
Author-email: darkfeline@felesatra.moe
License: UNKNOWN
Platform: UNKNOWN
Classifier: Development Status :: 4 - Beta
Classifier: Environment :: Console
Classifier: Intended Audience :: End Users/Desktop
Classifier: License :: OSI Approved :: Apache Software License
Classifier: Programming Language :: Python :: 3.6
